{
    "intents":[
        {
            "tag": "greeting",
            "patterns":[
                "hallo",
                "hai",
                "halo",
                "hei",
                "hi",
                "hy",
                "pagi",
                "morning",
                "siang",
                "afternoon",
                "sore",
                "malam",
                "bro",
                "sis",
                "kawan"
            ],
            "responses": [
                "Horas! MuseBot di sini. Mau tau informasi tentang apa nih?",
                "Ahoi! Saya MuseBot, salam kenal ya! Mau tau tentang Museum Deli Serdang, kan?",
                "Halo! Ini MuseBot. Lagi kepo tentang Museum Deli Serdang ya?"
            ]
        },
        {
            "tag": "MuseBot",
            "patterns" : [
                "Apa itu MuseBot?",
                "Siapa MuseBot ? "
            ],
            "responses":[
                "MuseBot adalah sebuat sistem layanan berbasis digital untuk membantu pengunjung untuk mengetahui apa saja layanan yang ada pada Museum ini .",
                "Musebot merupakan chatbot ......"
            ]
        },
        {
            "tag": "filosofi",
            "patterns":[
                "Apa filosofi dari bangunan Museum Deli Serdang ?",
                "Apa filosofi Museum deli serdang ? "
            ],
            "responses":[
                "filosofi dari bangunan museum Deli Serdang diambil dari konsep Itik Pulang Petang dari filosofi masyarakat Melayu. Ornamen 'Itik Pulang Petang' bermakna kepatuhan dan perlambang kebaikan, dimana unsur-unsur teratur, rapi dan harmonis tercermin dari bentuknya."
            ]
        },
        {
            "tag": "kapan",
            "patterns":[
                "Kapan didirikan museum deli serdang ?",
                ""
            ],
            "responses":[
                "Museum Deli Serdang merupakan museum khusus yang dibangun pada tahun 2001 dengan menggunakan dana Anggaran Pendapatan Belanja Daerah (APBD). Peresmian dilaksanakan pada tanggal 12 Agustus 2003."
            ]
        },
        {
            "tag": "goodbye",
            "patterns":[
                "Bye",
                "Sampai Jumpa",
                "Terimakasih",
                "See you..."
            ],
            "responses":[
                "Terimakasih telah menggunakan MuseBot",
                "See you again ...",
                "Bye ...",
                "Dadah..."
            ]
        }
    ]
}